LICENSE.md
README.md
setup.py
pysgt/GradHessStatsTest.py
pysgt/StochasticGradientTree.py
pysgt.egg-info/PKG-INFO
pysgt.egg-info/SOURCES.txt
pysgt.egg-info/dependency_links.txt
pysgt.egg-info/not-zip-safe
pysgt.egg-info/requires.txt
pysgt.egg-info/top_level.txt
pysgt/utils/FeatureInfo.py
pysgt/utils/GradHess.py
pysgt/utils/GradHessStats.py
pysgt/utils/OneVsRestClassifier.py
pysgt/utils/SoftmaxCrossEntropy.py
pysgt/utils/SquaredError.py
pysgt/utils/Statistics.py
pysgt/utils/StreamingGradientTree.py
pysgt/utils/StreamingGradientTreeNetwork.py
pysgt/utils/StreamingGradientTreeOptions.py