Metadata-Version: 2.1
Name: pysgt
Version: 1.0.3
Summary: Stochastic Gradient Trees implementation in Python
Home-page: https://github.com/JoKoum/stochastic-gradient-trees-python
Author: John Koumentis
Author-email: jokoum92@gmail.com
License: MIT
Platform: UNKNOWN
License-File: LICENSE.md
